synna_instructor/__init__.py
synna_instructor/cli/__init__.py
synna_instructor/cli/cli.py
synna_instructor/cli/files.py
synna_instructor/cli/jobs.py
synna_instructor/cli/usage.py
synna_instructor/dsl/__init__.py
synna_instructor/dsl/citation.py
synna_instructor/dsl/completion.py
synna_instructor/dsl/maybe.py
synna_instructor/dsl/messages/__init__.py
synna_instructor/dsl/messages/base.py
synna_instructor/dsl/messages/messages.py
synna_instructor/dsl/messages/user.py
synna_instructor/dsl/multitask.py
synna_instructor/dsl/validators.py
synna_instructor/examples/__init__.py
synna_instructor/examples/auto-ticketer/run.py
synna_instructor/examples/auto-ticketer/tasks.png
synna_instructor/examples/automatic_dataframe_extraction/auto_dataframe.py
synna_instructor/examples/automatic_dataframe_extraction/auto_multi_dataframe.py
synna_instructor/examples/citation_with_extraction/Dockerfile
synna_instructor/examples/citation_with_extraction/README.md
synna_instructor/examples/citation_with_extraction/citation_fuzzy_match.py
synna_instructor/examples/citation_with_extraction/diagram.py
synna_instructor/examples/citation_with_extraction/main.py
synna_instructor/examples/citation_with_extraction/modal_main.py
synna_instructor/examples/citation_with_extraction/requirements.txt
synna_instructor/examples/citation_with_extraction/schema.png
synna_instructor/examples/classification/multi_prediction.py
synna_instructor/examples/classification/simple_prediction.py
synna_instructor/examples/codegen-from-schema/create_fastapi_app.py
synna_instructor/examples/codegen-from-schema/input.json
synna_instructor/examples/codegen-from-schema/models.py
synna_instructor/examples/codegen-from-schema/readme.md
synna_instructor/examples/codegen-from-schema/run.py
synna_instructor/examples/evals/eval.py
synna_instructor/examples/evals/models.py
synna_instructor/examples/evals/stats_dict.py
synna_instructor/examples/evals/streamlit.py
synna_instructor/examples/evals/test.jsonl
synna_instructor-0.5.8.dist-info/LICENSE
synna_instructor-0.5.8.dist-info/METADATA
synna_instructor-0.5.8.dist-info/WHEEL
synna_instructor-0.5.8.dist-info/entry_points.txt
synna_instructor-0.5.8.dist-info/RECORD
