Metadata-Version: 2.1
Name: synna-instructor
Version: 0.5.8
Summary: Helper functions that allow us to improve openai's function_call ergonomics fork from jxnl/instructor
Home-page: https://github.com/hieutrluu/instructor
License: MIT
Author: Lewis
Author-email: lewis.luu@synna.ai
Requires-Python: >=3.9,<4.0
Classifier: License :: OSI Approved :: MIT License
Classifier: Programming Language :: Python :: 3
Classifier: Programming Language :: Python :: 3.9
Classifier: Programming Language :: Python :: 3.10
Classifier: Programming Language :: Python :: 3.11
Requires-Dist: docstring-parser (>=0.15,<0.16)
Requires-Dist: openai (>=0.27.8,<0.28.0)
Requires-Dist: pydantic (>=1.10.0,<2.0.0)
Requires-Dist: typer (>=0.9.0,<0.10.0)
Project-URL: Repository, https://github.com/hieutrluu/instructor
